LICENSE
MANIFEST.in
README.md
setup.cfg
setup.py
pokie_location/__init__.py
pokie_location/constants.py
pokie_location/module.py
pokie_location.egg-info/PKG-INFO
pokie_location.egg-info/SOURCES.txt
pokie_location.egg-info/dependency_links.txt
pokie_location.egg-info/not-zip-safe
pokie_location.egg-info/requires.txt
pokie_location.egg-info/top_level.txt
pokie_location/dao/__init__.py
pokie_location/service/__init__.py
pokie_location/service/location.py
pokie_location/sql/001-schema.sql
pokie_location/sql/002-country.sql
pokie_location/sql/003-timezone.sql